Workbook

Sheet Instructions
A1: Delivery Log Instructions
A2: Use of the Odometer and this Sheet:
A4: **Note: Use of this sheet requires that your vehicle's Odometer/Telemetry System must support both recording mileage and cumulative MPG for Trip A and Trip B**
A5: If these functions are not present on your vehicle, there are devices (like ScanGauge) that allow you to use the OBD-II port on your vehicle to interface with the ECU and directly view the data needed. In some cases, these devices can also directly monitor fuel usage.
A7: You will use "Trip A" to track each Rideshare/Delivery Trip's Distances and Cumulative MPG that you make. For the purposes of this calculator, a "Trip" is defined as the period that begins when you choose to start providing services until the end of your drive home, or at the moment you end services if you choose to go somewhere other than home at the end of your trip".
A8: Example: A "Trip" on DoorDash would begin when the "Dash Now" button was pressed and would end either at the end of your drive home, or at the moment your dash ended if you chose to drive somewhere other than home, for a non-delivery app related task. The home rule is used, as it is a key distinction with the IRS - this calculator was partially created to assist in maintaining accurate records for tax puposes. Just the same, a "Trip" on Uber would be the same protocol, but with "sessions" instead of "dashes".
A10: You will use "Trip B" to track your mileage and Cumulative MPG since your last refuel(s), which you will enter in sheet 'Refueling Log' (full instructions below). Your vehicle may be able to track this seperately from odometer features. Trip B will be used independently of Trip A, and will record both your personal and business usage (if your vehicle is used for both) to get the most acccurate measure of the cost basis of fuel in your tank. You will keep a seperate refueling log for each vehicle that you are measuring for.
A11: Prior to using this sheet for the first time, drive your vehicle as close to empty as you feel comfortable, then refill with a full tank and use the data for the first entry of the "Rolling Cost Basis Calculator" sheet.
A12: At the beginning of a new calendar year AND before your first drive, collect the "Trip B" Data (or use your vehicle monitoring device to collect the quantity of fuel in the tank)
A14: How To Use Delivery/Rideshare Log
A15: For the tracking of fueling expenses, open sheet "Refueling Log" and gather the data from Trip B (Fuel tracking) from your vehicle at the time of refueling as well as your receipt. With your receipt, gather the information for [Fueling Date & Time], [Fuel Added (Gallons)], and [Purchase Price of New Fuel (Per Gallon)]. With your vehicle's data, enter the information for [Distance Traveled Since Last Refuel (Miles)] and [Cumulative MPG Since Last Refuel]. The formulas will do the rest. IF TRACKING MULTIPLE VEHICLES: Make a copy of the "Refueling Log" Sheet and enter your vehicle's information. use the "Vehicle Used" field in the Monthly Logs to indicate and record for each vehicle in your fleet that was used. If you only have one vehicle, you can just list your Make, Model and Year to identify it. Data Validation Rules (Data->Data Validation Rules) can be helpful for this section
A16: For Delivery and Rideshare logging, you will utilize the "Trip A" data (Trip Tracking) from your vehicle's odometer/telemetry system to fill in the fields for [Total Trip Distance] and [Trip Average MPG]. You will then use the data from your Delivery/Ridesharing App to enter in the fields for [Start Time], [End Time], [Platform], [Offers], [Deliveries/Rides], and [Gross Earnings]. Again, the formulas will record the rest.
... A20: DO NOT EDIT CELL K1 IN THE "SUMMARY" SHEET OR CELL J1 IN ANY OF THE MONTHLY LOGS - This cell is used to convert the time format into a decimal number that is be used by various formulas. Editing this cell will crash the sheet.

Sheet Summary
A1: Delivery and Rideshare Log
A2: For the year of :
A3: Month | B3: Total Gross Earnings | C3: Total Fuel Cost | D3: Total Net Earnings | E3: Total Time | F3: Total Mileage | G3: Gross Earnings Per Hour | H3: Net Earnings Per Hour | I3: Gross Earnings Per Mile | J3: Net Earnings Per Mile | K3: 0.041666667
A4: January | B4: =JAN!M1 -> 0 | C4: =JAN!M2 -> 0 | D4: =B4-C4 -> 0 | E4: =JAN!O1 -> 0 | F4: =JAN!Q1 -> 0 | G4: =B4/(E4/$K$3) -> #DIV/0! | H4: =(B4-C4)/(E4/$K$3) -> #DIV/0! | I4: =B4/F4 -> #DIV/0! | J4: =(B4-C4)/F4 -> #DIV/0!
A5: February | B5: =FEB!M1 -> 0 | C5: =FEB!M2 -> 0 | D5: =B5-C5 -> 0 | E5: =FEB!O1 -> 0 | F5: =FEB!Q1 -> 0 | G5: =B5/(E5/$K$3) -> #DIV/0! | H5: =(B5-C5)/(E5/$K$3) -> #DIV/0! | I5: =B5/F5 -> #DIV/0! | J5: =(B5-C5)/F5 -> #DIV/0!
A6: March | B6: =MAR!M1 -> 0 | C6: =MAR!M2 -> 0 | D6: =B6-C6 -> 0 | E6: =MAR!O1 -> 0 | F6: =MAR!Q1 -> 0 | G6: =B6/(E6/$K$3) -> #DIV/0! | H6: =(B6-C6)/(E6/$K$3) -> #DIV/0! | I6: =B6/F6 -> #DIV/0! | J6: =(B6-C6)/F6 -> #DIV/0!
A7: April | B7: =APR!M1 -> 0 | C7: =APR!M2 -> 0 | D7: =B7-C7 -> 0 | E7: =APR!O1 -> 0 | F7: =APR!Q1 -> 0 | G7: =B7/(E7/$K$3) -> #DIV/0! | H7: =(B7-C7)/(E7/$K$3) -> #DIV/0! | I7: =B7/F7 -> #DIV/0! | J7: =(B7-C7)/F7 -> #DIV/0!
A8: May | B8: =MAY!M1 -> 0 | C8: =MAY!M2 -> 0 | D8: =B8-C8 -> 0 | E8: =MAY!O1 -> 0 | F8: =MAY!Q1 -> 0 | G8: =B8/(E8/$K$3) -> #DIV/0! | H8: =(B8-C8)/(E8/$K$3) -> #DIV/0! | I8: =B8/F8 -> #DIV/0! | J8: =(B8-C8)/F8 -> #DIV/0!
A9: June | B9: =JUN!M1 -> 0 | C9: =JUN!M2 -> 0 | D9: =B9-C9 -> 0 | E9: =JUN!O1 -> 0 | F9: =JUN!Q1 -> 0 | G9: =B9/(E9/$K$3) -> #DIV/0! | H9: =(B9-C9)/(E9/$K$3) -> #DIV/0! | I9: =B9/F9 -> #DIV/0! | J9: =(B9-C9)/F9 -> #DIV/0!
A10: July | B10: =JLY!M1 -> 0 | C10: =JLY!M2 -> 0 | D10: =B10-C10 -> 0 | E10: =JLY!O1 -> 0 | F10: =JLY!Q1 -> 0 | G10: =B10/(E10/$K$3) -> #DIV/0! | H10: =(B10-C10)/(E10/$K$3) -> #DIV/0! | I10: =B10/F10 -> #DIV/0! | J10: =(B10-C10)/F10 -> #DIV/0!
A11: August | B11: =AUG!M1 -> 0 | C11: =AUG!M2 -> 0 | D11: =B11-C11 -> 0 | E11: =AUG!O1 -> 0 | F11: =AUG!Q1 -> 0 | G11: =B11/(E11/$K$3) -> #DIV/0! | H11: =(B11-C11)/(E11/$K$3) -> #DIV/0! | I11: =B11/F11 -> #DIV/0! | J11: =(B11-C11)/F11 -> #DIV/0!
A12: September | B12: =SEP!M1 -> 0 | C12: =SEP!M2 -> 0 | D12: =B12-C12 -> 0 | E12: =SEP!O1 -> 0 | F12: =SEP!Q1 -> 0 | G12: =B12/(E12/$K$3) -> #DIV/0! | H12: =(B12-C12)/(E12/$K$3) -> #DIV/0! | I12: =B12/F12 -> #DIV/0! | J12: =(B12-C12)/F12 -> #DIV/0!
A13: October | B13: =OCT!M1 -> 0 | C13: =OCT!M2 -> 0 | D13: =B13-C13 -> 0 | E13: =OCT!O1 -> 0 | F13: =OCT!Q1 -> 0 | G13: =B13/(E13/$K$3) -> #DIV/0! | H13: =(B13-C13)/(E13/$K$3) -> #DIV/0! | I13: =B13/F13 -> #DIV/0! | J13: =(B13-C13)/F13 -> #DIV/0!
A14: November | B14: =NOV!M1 -> 0 | C14: =NOV!M2 -> 0 | D14: =B14-C14 -> 0 | E14: =NOV!O1 -> 0 | F14: =NOV!Q1 -> 0 | G14: =B14/(E14/$K$3) -> #DIV/0! | H14: =(B14-C14)/(E14/$K$3) -> #DIV/0! | I14: =B14/F14 -> #DIV/0! | J14: =(B14-C14)/F14 -> #DIV/0!
A15: December | B15: =DEC!M1 -> 0 | C15: =DEC!M2 -> 0 | D15: =B15-C15 -> 0 | E15: =DEC!O1 -> 0 | F15: =DEC!Q1 -> 0 | G15: =B15/(E15/$K$3) -> #DIV/0! | H15: =(B15-C15)/(E15/$K$3) -> #DIV/0! | I15: =B15/F15 -> #DIV/0! | J15: =(B15-C15)/F15 -> #DIV/0!
A17: Grand Total | B17: =SUM(B4:B15) -> 0 | C17: =SUM(C4:C15) -> 0 | D17: =SUM(D4:D15) -> 0 | E17: =SUM(E4:E15) -> 0 | F17: =SUM(F4:F15) -> 0 | G17: =B17/(E17/K3) -> #DIV/0! | H17: =(B17-C17)/(E17/K3) -> #DIV/0! | I17: =B17/F17 -> #DIV/0! | J17: =(B17-C17)/F17 -> #DIV/0!

Sheet Refueling Log
A1: Vehicle: | C1: Year Start Mileage: | E1: Year End Mileage
A2: Current Cost Basis of Fuel (Per Gallon) | B2: {=INDEX(G:G, MAX(IF(G4:G1005<>"", ROW(G4:G1005))))} -> 0 | C2: Most Recent Fueling | D2: {=INDEX(A:A, MAX(IF(A4:A1005<>"", ROW(A4:A1005))))} -> 01/01/20XX 00:00:00 | E2: Total Fuel Expenditure YTD | F2: =SUMPRODUCT(E4:E1005,F4:F1005) -> 0
A3: Fueling Date & Time | B3: Distance Traveled Since Last Refuel (TRIP B Miles) | C3: Cumulative MPG Since Last Refuel (TRIP B MPG) | D3: Current Fuel (Gallons) | E3: Fuel Added (Gallons) | F3: Purchase Price of New Fuel (Per Gallon) | G3: Cost Basis of Current Fuel (Per Gallon) | H3: New Total Fuel Quantity (Gallons) | I3: New Total Cost Basis (Per Gallon)
A4: 01/01/20XX 00:00:00 | B4: 0 | C4: 0 | D4: 0 | E4: 0 | F4: 0 | G4: 0 | H4: =IFERROR(IF(D4+E4>0,D4+E4,""),"") | I4: =IFERROR((G4*(D4/(D4+E4))+(F4*(E4/(D4+E4)))),"")
D5: =IFERROR(H4-(B5/C5),"") | G5: =I4 | H5: =IFERROR(IF(D5+E5>0,D5+E5,""),"") | I5: =IFERROR((G5*(D5/(D5+E5))+(F5*(E5/(D5+E5)))),"")
D6: =IFERROR(H5-(B6/C6),"") | G6: =I5 | H6: =IFERROR(IF(D6+E6>0,D6+E6,""),"") | I6: =IFERROR((G6*(D6/(D6+E6))+(F6*(E6/(D6+E6)))),"")
D7: =IFERROR(H6-(B7/C7),"") | G7: =I6 | H7: =IFERROR(IF(D7+E7>0,D7+E7,""),"") | I7: =IFERROR((G7*(D7/(D7+E7))+(F7*(E7/(D7+E7)))),"")
D8: =IFERROR(H7-(B8/C8),"") | G8: =I7 | H8: =IFERROR(IF(D8+E8>0,D8+E8,""),"") | I8: =IFERROR((G8*(D8/(D8+E8))+(F8*(E8/(D8+E8)))),"")
D9: =IFERROR(H8-(B9/C9),"") | G9: =I8 | H9: =IFERROR(IF(D9+E9>0,D9+E9,""),"") | I9: =IFERROR((G9*(D9/(D9+E9))+(F9*(E9/(D9+E9)))),"")
D10: =IFERROR(H9-(B10/C10),"") | G10: =I9 | H10: =IFERROR(IF(D10+E10>0,D10+E10,""),"") | I10: =IFERROR((G10*(D10/(D10+E10))+(F10*(E10/(D10+E10)))),"")
D11: =IFERROR(H10-(B11/C11),"") | G11: =I10 | H11: =IFERROR(IF(D11+E11>0,D11+E11,""),"") | I11: =IFERROR((G11*(D11/(D11+E11))+(F11*(E11/(D11+E11)))),"")
D12: =IFERROR(H11-(B12/C12),"") | G12: =I11 | H12: =IFERROR(IF(D12+E12>0,D12+E12,""),"") | I12: =IFERROR((G12*(D12/(D12+E12))+(F12*(E12/(D12+E12)))),"")
D13: =IFERROR(H12-(B13/C13),"") | G13: =I12 | H13: =IFERROR(IF(D13+E13>0,D13+E13,""),"") | I13: =IFERROR((G13*(D13/(D13+E13))+(F13*(E13/(D13+E13)))),"")
D14: =IFERROR(H13-(B14/C14),"") | G14: =I13 | H14: =IFERROR(IF(D14+E14>0,D14+E14,""),"") | I14: =IFERROR((G14*(D14/(D14+E14))+(F14*(E14/(D14+E14)))),"")
D15: =IFERROR(H14-(B15/C15),"") | G15: =I14 | H15: =IFERROR(IF(D15+E15>0,D15+E15,""),"") | I15: =IFERROR((G15*(D15/(D15+E15))+(F15*(E15/(D15+E15)))),"")
D16: =IFERROR(H15-(B16/C16),"") | G16: =I15 | H16: =IFERROR(IF(D16+E16>0,D16+E16,""),"") | I16: =IFERROR((G16*(D16/(D16+E16))+(F16*(E16/(D16+E16)))),"")
... D1005: =IFERROR(H1004-(B1005/C1005),"") | G1005: =I1004 | H1005: =IFERROR(IF(D1005+E1005>0,D1005+E1005,""),"") | I1005: =IFERROR((G1005*(D1005/(D1005+E1005))+(F1005*(E1005/(D1005+E1005)))),"")

Sheet JAN
A1: JANUARY | C1: =Summary!C2 -> 0 | K1: 0.041666667 | L1: Total Gross Earnings | M1: =SUM(K5:K505) -> 0 | N1: Total Time | O1: =SUM(C5:C505) -> 0 | P1: Total Mileage | Q1: =SUM(H5:H505) -> 0
L2: Total Fuel Cost | M2: =SUM(L:L) -> 0 | N2: Average Gross Per Hour | O2: =IFERROR(M1/(O1/$K$1),"") | P2: Gross Earnings Per Mile | Q2: =IFERROR(M1/Q1,"")
L3: Total Net Earnings | M3: =M1-M2 -> 0 | N3: Average Net Per Hour | O3: =IFERROR((M1-M2)/(O1/$K$1),"") | P3: Net Earnings Per Mile | Q3: =IFERROR((M1-M2)/Q1,"")
A4: Start Time | B4: End Time | C4: Trip Duration | D4: Vehicle Used | E4: Platform | F4: Accepted Offers | G4: Deliveries/Rides | H4: Total Trip Distance | I4: Trip Average MPG | J4: Current Cost Basis of Fuel (Per Gallon) | K4: Gross Earnings | L4: Trip Fuel Cost | M4: Net Earnings | N4: Gross Earnings Per Hour | O4: Net Earnings Per Hour | P4: Gross Earnings Per Mile | Q4: Net Earnings Per Mile
C5: =IF(B5-A5>0,B5-A5,"") | L5: =IFERROR(J5*(H5/I5),"") | M5: =IFERROR(IF(K5-L5>0,K5-L5,""),"") | N5: =IFERROR(K5/(C5/$K$1),"") | O5: =IFERROR(M5/(C5/$K$1),"") | P5: =IFERROR(K5/H5,"") | Q5: =IFERROR((K5-L5)/H5,"")
C6: =IF(B6-A6>0,B6-A6,"") | L6: =IFERROR(J6*(H6/I6),"") | M6: =IFERROR(IF(K6-L6>0,K6-L6,""),"") | N6: =IFERROR(K6/(C6/$K$1),"") | O6: =IFERROR(M6/(C6/$K$1),"") | P6: =IFERROR(K6/H6,"") | Q6: =IFERROR((K6-L6)/H6,"")
C7: =IF(B7-A7>0,B7-A7,"") | L7: =IFERROR(J7*(H7/I7),"") | M7: =IFERROR(IF(K7-L7>0,K7-L7,""),"") | N7: =IFERROR(K7/(C7/$K$1),"") | O7: =IFERROR(M7/(C7/$K$1),"") | P7: =IFERROR(K7/H7,"") | Q7: =IFERROR((K7-L7)/H7,"")
C8: =IF(B8-A8>0,B8-A8,"") | L8: =IFERROR(J8*(H8/I8),"") | M8: =IFERROR(IF(K8-L8>0,K8-L8,""),"") | N8: =IFERROR(K8/(C8/$K$1),"") | O8: =IFERROR(M8/(C8/$K$1),"") | P8: =IFERROR(K8/H8,"") | Q8: =IFERROR((K8-L8)/H8,"")
C9: =IF(B9-A9>0,B9-A9,"") | L9: =IFERROR(J9*(H9/I9),"") | M9: =IFERROR(IF(K9-L9>0,K9-L9,""),"") | N9: =IFERROR(K9/(C9/$K$1),"") | O9: =IFERROR(M9/(C9/$K$1),"") | P9: =IFERROR(K9/H9,"") | Q9: =IFERROR((K9-L9)/H9,"")
C10: =IF(B10-A10>0,B10-A10,"") | L10: =IFERROR(J10*(H10/I10),"") | M10: =IFERROR(IF(K10-L10>0,K10-L10,""),"") | N10: =IFERROR(K10/(C10/$K$1),"") | O10: =IFERROR(M10/(C10/$K$1),"") | P10: =IFERROR(K10/H10,"") | Q10: =IFERROR((K10-L10)/H10,"")
C11: =IF(B11-A11>0,B11-A11,"") | L11: =IFERROR(J11*(H11/I11),"") | M11: =IFERROR(IF(K11-L11>0,K11-L11,""),"") | N11: =IFERROR(K11/(C11/$K$1),"") | O11: =IFERROR(M11/(C11/$K$1),"") | P11: =IFERROR(K11/H11,"") | Q11: =IFERROR((K11-L11)/H11,"")
C12: =IF(B12-A12>0,B12-A12,"") | L12: =IFERROR(J12*(H12/I12),"") | M12: =IFERROR(IF(K12-L12>0,K12-L12,""),"") | N12: =IFERROR(K12/(C12/$K$1),"") | O12: =IFERROR(M12/(C12/$K$1),"") | P12: =IFERROR(K12/H12,"") | Q12: =IFERROR((K12-L12)/H12,"")
C13: =IF(B13-A13>0,B13-A13,"") | L13: =IFERROR(J13*(H13/I13),"") | M13: =IFERROR(IF(K13-L13>0,K13-L13,""),"") | N13: =IFERROR(K13/(C13/$K$1),"") | O13: =IFERROR(M13/(C13/$K$1),"") | P13: =IFERROR(K13/H13,"") | Q13: =IFERROR((K13-L13)/H13,"")
C14: =IF(B14-A14>0,B14-A14,"") | L14: =IFERROR(J14*(H14/I14),"") | M14: =IFERROR(IF(K14-L14>0,K14-L14,""),"") | N14: =IFERROR(K14/(C14/$K$1),"") | O14: =IFERROR(M14/(C14/$K$1),"") | P14: =IFERROR(K14/H14,"") | Q14: =IFERROR((K14-L14)/H14,"")
C15: =IF(B15-A15>0,B15-A15,"") | L15: =IFERROR(J15*(H15/I15),"") | M15: =IFERROR(IF(K15-L15>0,K15-L15,""),"") | N15: =IFERROR(K15/(C15/$K$1),"") | O15: =IFERROR(M15/(C15/$K$1),"") | P15: =IFERROR(K15/H15,"") | Q15: =IFERROR((K15-L15)/H15,"")
C16: =IF(B16-A16>0,B16-A16,"") | L16: =IFERROR(J16*(H16/I16),"") | M16: =IFERROR(IF(K16-L16>0,K16-L16,""),"") | N16: =IFERROR(K16/(C16/$K$1),"") | O16: =IFERROR(M16/(C16/$K$1),"") | P16: =IFERROR(K16/H16,"") | Q16: =IFERROR((K16-L16)/H16,"")
... C505: =IF(B505-A505>0,B505-A505,"") | L505: =IFERROR(J505*(H505/I505),"") | M505: =IFERROR(IF(K505-L505>0,K505-L505,""),"") | N505: =IFERROR(K505/(C505/$K$1),"") | O505: =IFERROR(M505/(C505/$K$1),"") | P505: =IFERROR(K505/H505,"") | Q505: =IFERROR((K505-L505)/H505,"")

Sheet FEB
A1: FEBRUARY | C1: =Summary!C2 -> 0 | K1: 0.041666667 | L1: Total Gross Earnings | M1: =SUM(K5:K505) -> 0 | N1: Total Time | O1: =SUM(C5:C505) -> 0 | P1: Total Mileage | Q1: =SUM(H5:H505) -> 0
L2: Total Fuel Cost | M2: =SUM(L:L) -> 0 | N2: Average Gross Per Hour | O2: =IFERROR(M1/(O1/$K$1),"") | P2: Gross Earnings Per Mile | Q2: =IFERROR(M1/Q1,"")
L3: Total Net Earnings | M3: =M1-M2 -> 0 | N3: Average Net Per Hour | O3: =IFERROR((M1-M2)/(O1/$K$1),"") | P3: Net Earnings Per Mile | Q3: =IFERROR((M1-M2)/Q1,"")
A4: Start Time | B4: End Time | C4: Trip Duration | D4: Vehicle Used | E4: Platform | F4: Accepted Offers | G4: Deliveries/Rides | H4: Total Trip Distance | I4: Trip Average MPG | J4: Current Cost Basis of Fuel (Per Gallon) | K4: Gross Earnings | L4: Trip Fuel Cost | M4: Net Earnings | N4: Gross Earnings Per Hour | O4: Net Earnings Per Hour | P4: Gross Earnings Per Mile | Q4: Net Earnings Per Mile
C5: =IF(B5-A5>0,B5-A5,"") | L5: =IFERROR(J5*(H5/I5),"") | M5: =IFERROR(IF(K5-L5>0,K5-L5,""),"") | N5: =IFERROR(K5/(C5/$K$1),"") | O5: =IFERROR(M5/(C5/$K$1),"") | P5: =IFERROR(K5/H5,"") | Q5: =IFERROR((K5-L5)/H5,"")
C6: =IF(B6-A6>0,B6-A6,"") | L6: =IFERROR(J6*(H6/I6),"") | M6: =IFERROR(IF(K6-L6>0,K6-L6,""),"") | N6: =IFERROR(K6/(C6/$K$1),"") | O6: =IFERROR(M6/(C6/$K$1),"") | P6: =IFERROR(K6/H6,"") | Q6: =IFERROR((K6-L6)/H6,"")
C7: =IF(B7-A7>0,B7-A7,"") | L7: =IFERROR(J7*(H7/I7),"") | M7: =IFERROR(IF(K7-L7>0,K7-L7,""),"") | N7: =IFERROR(K7/(C7/$K$1),"") | O7: =IFERROR(M7/(C7/$K$1),"") | P7: =IFERROR(K7/H7,"") | Q7: =IFERROR((K7-L7)/H7,"")
C8: =IF(B8-A8>0,B8-A8,"") | L8: =IFERROR(J8*(H8/I8),"") | M8: =IFERROR(IF(K8-L8>0,K8-L8,""),"") | N8: =IFERROR(K8/(C8/$K$1),"") | O8: =IFERROR(M8/(C8/$K$1),"") | P8: =IFERROR(K8/H8,"") | Q8: =IFERROR((K8-L8)/H8,"")
C9: =IF(B9-A9>0,B9-A9,"") | L9: =IFERROR(J9*(H9/I9),"") | M9: =IFERROR(IF(K9-L9>0,K9-L9,""),"") | N9: =IFERROR(K9/(C9/$K$1),"") | O9: =IFERROR(M9/(C9/$K$1),"") | P9: =IFERROR(K9/H9,"") | Q9: =IFERROR((K9-L9)/H9,"")
C10: =IF(B10-A10>0,B10-A10,"") | L10: =IFERROR(J10*(H10/I10),"") | M10: =IFERROR(IF(K10-L10>0,K10-L10,""),"") | N10: =IFERROR(K10/(C10/$K$1),"") | O10: =IFERROR(M10/(C10/$K$1),"") | P10: =IFERROR(K10/H10,"") | Q10: =IFERROR((K10-L10)/H10,"")
C11: =IF(B11-A11>0,B11-A11,"") | L11: =IFERROR(J11*(H11/I11),"") | M11: =IFERROR(IF(K11-L11>0,K11-L11,""),"") | N11: =IFERROR(K11/(C11/$K$1),"") | O11: =IFERROR(M11/(C11/$K$1),"") | P11: =IFERROR(K11/H11,"") | Q11: =IFERROR((K11-L11)/H11,"")
C12: =IF(B12-A12>0,B12-A12,"") | L12: =IFERROR(J12*(H12/I12),"") | M12: =IFERROR(IF(K12-L12>0,K12-L12,""),"") | N12: =IFERROR(K12/(C12/$K$1),"") | O12: =IFERROR(M12/(C12/$K$1),"") | P12: =IFERROR(K12/H12,"") | Q12: =IFERROR((K12-L12)/H12,"")
C13: =IF(B13-A13>0,B13-A13,"") | L13: =IFERROR(J13*(H13/I13),"") | M13: =IFERROR(IF(K13-L13>0,K13-L13,""),"") | N13: =IFERROR(K13/(C13/$K$1),"") | O13: =IFERROR(M13/(C13/$K$1),"") | P13: =IFERROR(K13/H13,"") | Q13: =IFERROR((K13-L13)/H13,"")
C14: =IF(B14-A14>0,B14-A14,"") | L14: =IFERROR(J14*(H14/I14),"") | M14: =IFERROR(IF(K14-L14>0,K14-L14,""),"") | N14: =IFERROR(K14/(C14/$K$1),"") | O14: =IFERROR(M14/(C14/$K$1),"") | P14: =IFERROR(K14/H14,"") | Q14: =IFERROR((K14-L14)/H14,"")
C15: =IF(B15-A15>0,B15-A15,"") | L15: =IFERROR(J15*(H15/I15),"") | M15: =IFERROR(IF(K15-L15>0,K15-L15,""),"") | N15: =IFERROR(K15/(C15/$K$1),"") | O15: =IFERROR(M15/(C15/$K$1),"") | P15: =IFERROR(K15/H15,"") | Q15: =IFERROR((K15-L15)/H15,"")
C16: =IF(B16-A16>0,B16-A16,"") | L16: =IFERROR(J16*(H16/I16),"") | M16: =IFERROR(IF(K16-L16>0,K16-L16,""),"") | N16: =IFERROR(K16/(C16/$K$1),"") | O16: =IFERROR(M16/(C16/$K$1),"") | P16: =IFERROR(K16/H16,"") | Q16: =IFERROR((K16-L16)/H16,"")
... C505: =IF(B505-A505>0,B505-A505,"") | L505: =IFERROR(J505*(H505/I505),"") | M505: =IFERROR(IF(K505-L505>0,K505-L505,""),"") | N505: =IFERROR(K505/(C505/$K$1),"") | O505: =IFERROR(M505/(C505/$K$1),"") | P505: =IFERROR(K505/H505,"") | Q505: =IFERROR((K505-L505)/H505,"")

Sheet MAR
A1: MARCH | C1: =Summary!C2 -> 0 | K1: 0.041666667 | L1: Total Gross Earnings | M1: =SUM(K5:K505) -> 0 | N1: Total Time | O1: =SUM(C5:C505) -> 0 | P1: Total Mileage | Q1: =SUM(H5:H505) -> 0
L2: Total Fuel Cost | M2: =SUM(L:L) -> 0 | N2: Average Gross Per Hour | O2: =IFERROR(M1/(O1/$K$1),"") | P2: Gross Earnings Per Mile | Q2: =IFERROR(M1/Q1,"")
L3: Total Net Earnings | M3: =M1-M2 -> 0 | N3: Average Net Per Hour | O3: =IFERROR((M1-M2)/(O1/$K$1),"") | P3: Net Earnings Per Mile | Q3: =IFERROR((M1-M2)/Q1,"")
A4: Start Time | B4: End Time | C4: Trip Duration | D4: Vehicle Used | E4: Platform | F4: Accepted Offers | G4: Deliveries/Rides | H4: Total Trip Distance | I4: Trip Average MPG | J4: Current Cost Basis of Fuel (Per Gallon) | K4: Gross Earnings | L4: Trip Fuel Cost | M4: Net Earnings | N4: Gross Earnings Per Hour | O4: Net Earnings Per Hour | P4: Gross Earnings Per Mile | Q4: Net Earnings Per Mile
C5: =IF(B5-A5>0,B5-A5,"") | L5: =IFERROR(J5*(H5/I5),"") | M5: =IFERROR(IF(K5-L5>0,K5-L5,""),"") | N5: =IFERROR(K5/(C5/$K$1),"") | O5: =IFERROR(M5/(C5/$K$1),"") | P5: =IFERROR(K5/H5,"") | Q5: =IFERROR((K5-L5)/H5,"")
C6: =IF(B6-A6>0,B6-A6,"") | L6: =IFERROR(J6*(H6/I6),"") | M6: =IFERROR(IF(K6-L6>0,K6-L6,""),"") | N6: =IFERROR(K6/(C6/$K$1),"") | O6: =IFERROR(M6/(C6/$K$1),"") | P6: =IFERROR(K6/H6,"") | Q6: =IFERROR((K6-L6)/H6,"")
C7: =IF(B7-A7>0,B7-A7,"") | L7: =IFERROR(J7*(H7/I7),"") | M7: =IFERROR(IF(K7-L7>0,K7-L7,""),"") | N7: =IFERROR(K7/(C7/$K$1),"") | O7: =IFERROR(M7/(C7/$K$1),"") | P7: =IFERROR(K7/H7,"") | Q7: =IFERROR((K7-L7)/H7,"")
C8: =IF(B8-A8>0,B8-A8,"") | L8: =IFERROR(J8*(H8/I8),"") | M8: =IFERROR(IF(K8-L8>0,K8-L8,""),"") | N8: =IFERROR(K8/(C8/$K$1),"") | O8: =IFERROR(M8/(C8/$K$1),"") | P8: =IFERROR(K8/H8,"") | Q8: =IFERROR((K8-L8)/H8,"")
C9: =IF(B9-A9>0,B9-A9,"") | L9: =IFERROR(J9*(H9/I9),"") | M9: =IFERROR(IF(K9-L9>0,K9-L9,""),"") | N9: =IFERROR(K9/(C9/$K$1),"") | O9: =IFERROR(M9/(C9/$K$1),"") | P9: =IFERROR(K9/H9,"") | Q9: =IFERROR((K9-L9)/H9,"")
C10: =IF(B10-A10>0,B10-A10,"") | L10: =IFERROR(J10*(H10/I10),"") | M10: =IFERROR(IF(K10-L10>0,K10-L10,""),"") | N10: =IFERROR(K10/(C10/$K$1),"") | O10: =IFERROR(M10/(C10/$K$1),"") | P10: =IFERROR(K10/H10,"") | Q10: =IFERROR((K10-L10)/H10,"")
C11: =IF(B11-A11>0,B11-A11,"") | L11: =IFERROR(J11*(H11/I11),"") | M11: =IFERROR(IF(K11-L11>0,K11-L11,""),"") | N11: =IFERROR(K11/(C11/$K$1),"") | O11: =IFERROR(M11/(C11/$K$1),"") | P11: =IFERROR(K11/H11,"") | Q11: =IFERROR((K11-L11)/H11,"")
C12: =IF(B12-A12>0,B12-A12,"") | L12: =IFERROR(J12*(H12/I12),"") | M12: =IFERROR(IF(K12-L12>0,K12-L12,""),"") | N12: =IFERROR(K12/(C12/$K$1),"") | O12: =IFERROR(M12/(C12/$K$1),"") | P12: =IFERROR(K12/H12,"") | Q12: =IFERROR((K12-L12)/H12,"")
C13: =IF(B13-A13>0,B13-A13,"") | L13: =IFERROR(J13*(H13/I13),"") | M13: =IFERROR(IF(K13-L13>0,K13-L13,""),"") | N13: =IFERROR(K13/(C13/$K$1),"") | O13: =IFERROR(M13/(C13/$K$1),"") | P13: =IFERROR(K13/H13,"") | Q13: =IFERROR((K13-L13)/H13,"")
C14: =IF(B14-A14>0,B14-A14,"") | L14: =IFERROR(J14*(H14/I14),"") | M14: =IFERROR(IF(K14-L14>0,K14-L14,""),"") | N14: =IFERROR(K14/(C14/$K$1),"") | O14: =IFERROR(M14/(C14/$K$1),"") | P14: =IFERROR(K14/H14,"") | Q14: =IFERROR((K14-L14)/H14,"")
C15: =IF(B15-A15>0,B15-A15,"") | L15: =IFERROR(J15*(H15/I15),"") | M15: =IFERROR(IF(K15-L15>0,K15-L15,""),"") | N15: =IFERROR(K15/(C15/$K$1),"") | O15: =IFERROR(M15/(C15/$K$1),"") | P15: =IFERROR(K15/H15,"") | Q15: =IFERROR((K15-L15)/H15,"")
C16: =IF(B16-A16>0,B16-A16,"") | L16: =IFERROR(J16*(H16/I16),"") | M16: =IFERROR(IF(K16-L16>0,K16-L16,""),"") | N16: =IFERROR(K16/(C16/$K$1),"") | O16: =IFERROR(M16/(C16/$K$1),"") | P16: =IFERROR(K16/H16,"") | Q16: =IFERROR((K16-L16)/H16,"")
... C505: =IF(B505-A505>0,B505-A505,"") | L505: =IFERROR(J505*(H505/I505),"") | M505: =IFERROR(IF(K505-L505>0,K505-L505,""),"") | N505: =IFERROR(K505/(C505/$K$1),"") | O505: =IFERROR(M505/(C505/$K$1),"") | P505: =IFERROR(K505/H505,"") | Q505: =IFERROR((K505-L505)/H505,"")

Sheet APR
A1: APRIL | C1: =Summary!C2 -> 0 | K1: 0.041666667 | L1: Total Gross Earnings | M1: =SUM(K5:K505) -> 0 | N1: Total Time | O1: =SUM(C5:C505) -> 0 | P1: Total Mileage | Q1: =SUM(H5:H505) -> 0
L2: Total Fuel Cost | M2: =SUM(L:L) -> 0 | N2: Average Gross Per Hour | O2: =IFERROR(M1/(O1/$K$1),"") | P2: Gross Earnings Per Mile | Q2: =IFERROR(M1/Q1,"")
L3: Total Net Earnings | M3: =M1-M2 -> 0 | N3: Average Net Per Hour | O3: =IFERROR((M1-M2)/(O1/$K$1),"") | P3: Net Earnings Per Mile | Q3: =IFERROR((M1-M2)/Q1,"")
A4: Start Time | B4: End Time | C4: Trip Duration | D4: Vehicle Used | E4: Platform | F4: Accepted Offers | G4: Deliveries/Rides | H4: Total Trip Distance | I4: Trip Average MPG | J4: Current Cost Basis of Fuel (Per Gallon) | K4: Gross Earnings | L4: Trip Fuel Cost | M4: Net Earnings | N4: Gross Earnings Per Hour | O4: Net Earnings Per Hour | P4: Gross Earnings Per Mile | Q4: Net Earnings Per Mile
C5: =IF(B5-A5>0,B5-A5,"") | L5: =IFERROR(J5*(H5/I5),"") | M5: =IFERROR(IF(K5-L5>0,K5-L5,""),"") | N5: =IFERROR(K5/(C5/$K$1),"") | O5: =IFERROR(M5/(C5/$K$1),"") | P5: =IFERROR(K5/H5,"") | Q5: =IFERROR((K5-L5)/H5,"")
C6: =IF(B6-A6>0,B6-A6,"") | L6: =IFERROR(J6*(H6/I6),"") | M6: =IFERROR(IF(K6-L6>0,K6-L6,""),"") | N6: =IFERROR(K6/(C6/$K$1),"") | O6: =IFERROR(M6/(C6/$K$1),"") | P6: =IFERROR(K6/H6,"") | Q6: =IFERROR((K6-L6)/H6,"")
C7: =IF(B7-A7>0,B7-A7,"") | L7: =IFERROR(J7*(H7/I7),"") | M7: =IFERROR(IF(K7-L7>0,K7-L7,""),"") | N7: =IFERROR(K7/(C7/$K$1),"") | O7: =IFERROR(M7/(C7/$K$1),"") | P7: =IFERROR(K7/H7,"") | Q7: =IFERROR((K7-L7)/H7,"")
C8: =IF(B8-A8>0,B8-A8,"") | L8: =IFERROR(J8*(H8/I8),"") | M8: =IFERROR(IF(K8-L8>0,K8-L8,""),"") | N8: =IFERROR(K8/(C8/$K$1),"") | O8: =IFERROR(M8/(C8/$K$1),"") | P8: =IFERROR(K8/H8,"") | Q8: =IFERROR((K8-L8)/H8,"")
C9: =IF(B9-A9>0,B9-A9,"") | L9: =IFERROR(J9*(H9/I9),"") | M9: =IFERROR(IF(K9-L9>0,K9-L9,""),"") | N9: =IFERROR(K9/(C9/$K$1),"") | O9: =IFERROR(M9/(C9/$K$1),"") | P9: =IFERROR(K9/H9,"") | Q9: =IFERROR((K9-L9)/H9,"")
C10: =IF(B10-A10>0,B10-A10,"") | L10: =IFERROR(J10*(H10/I10),"") | M10: =IFERROR(IF(K10-L10>0,K10-L10,""),"") | N10: =IFERROR(K10/(C10/$K$1),"") | O10: =IFERROR(M10/(C10/$K$1),"") | P10: =IFERROR(K10/H10,"") | Q10: =IFERROR((K10-L10)/H10,"")
C11: =IF(B11-A11>0,B11-A11,"") | L11: =IFERROR(J11*(H11/I11),"") | M11: =IFERROR(IF(K11-L11>0,K11-L11,""),"") | N11: =IFERROR(K11/(C11/$K$1),"") | O11: =IFERROR(M11/(C11/$K$1),"") | P11: =IFERROR(K11/H11,"") | Q11: =IFERROR((K11-L11)/H11,"")
C12: =IF(B12-A12>0,B12-A12,"") | L12: =IFERROR(J12*(H12/I12),"") | M12: =IFERROR(IF(K12-L12>0,K12-L12,""),"") | N12: =IFERROR(K12/(C12/$K$1),"") | O12: =IFERROR(M12/(C12/$K$1),"") | P12: =IFERROR(K12/H12,"") | Q12: =IFERROR((K12-L12)/H12,"")
C13: =IF(B13-A13>0,B13-A13,"") | L13: =IFERROR(J13*(H13/I13),"") | M13: =IFERROR(IF(K13-L13>0,K13-L13,""),"") | N13: =IFERROR(K13/(C13/$K$1),"") | O13: =IFERROR(M13/(C13/$K$1),"") | P13: =IFERROR(K13/H13,"") | Q13: =IFERROR((K13-L13)/H13,"")
C14: =IF(B14-A14>0,B14-A14,"") | L14: =IFERROR(J14*(H14/I14),"") | M14: =IFERROR(IF(K14-L14>0,K14-L14,""),"") | N14: =IFERROR(K14/(C14/$K$1),"") | O14: =IFERROR(M14/(C14/$K$1),"") | P14: =IFERROR(K14/H14,"") | Q14: =IFERROR((K14-L14)/H14,"")
C15: =IF(B15-A15>0,B15-A15,"") | L15: =IFERROR(J15*(H15/I15),"") | M15: =IFERROR(IF(K15-L15>0,K15-L15,""),"") | N15: =IFERROR(K15/(C15/$K$1),"") | O15: =IFERROR(M15/(C15/$K$1),"") | P15: =IFERROR(K15/H15,"") | Q15: =IFERROR((K15-L15)/H15,"")
C16: =IF(B16-A16>0,B16-A16,"") | L16: =IFERROR(J16*(H16/I16),"") | M16: =IFERROR(IF(K16-L16>0,K16-L16,""),"") | N16: =IFERROR(K16/(C16/$K$1),"") | O16: =IFERROR(M16/(C16/$K$1),"") | P16: =IFERROR(K16/H16,"") | Q16: =IFERROR((K16-L16)/H16,"")
... C505: =IF(B505-A505>0,B505-A505,"") | L505: =IFERROR(J505*(H505/I505),"") | M505: =IFERROR(IF(K505-L505>0,K505-L505,""),"") | N505: =IFERROR(K505/(C505/$K$1),"") | O505: =IFERROR(M505/(C505/$K$1),"") | P505: =IFERROR(K505/H505,"") | Q505: =IFERROR((K505-L505)/H505,"")

Sheet MAY
A1: MAY | C1: =Summary!C2 -> 0 | K1: 0.041666667 | L1: Total Gross Earnings | M1: =SUM(K5:K505) -> 0 | N1: Total Time | O1: =SUM(C5:C505) -> 0 | P1: Total Mileage | Q1: =SUM(H5:H505) -> 0
L2: Total Fuel Cost | M2: =SUM(L:L) -> 0 | N2: Average Gross Per Hour | O2: =IFERROR(M1/(O1/$K$1),"") | P2: Gross Earnings Per Mile | Q2: =IFERROR(M1/Q1,"")
L3: Total Net Earnings | M3: =M1-M2 -> 0 | N3: Average Net Per Hour | O3: =IFERROR((M1-M2)/(O1/$K$1),"") | P3: Net Earnings Per Mile | Q3: =IFERROR((M1-M2)/Q1,"")
A4: Start Time | B4: End Time | C4: Trip Duration | D4: Vehicle Used | E4: Platform | F4: Accepted Offers | G4: Deliveries/Rides | H4: Total Trip Distance | I4: Trip Average MPG | J4: Current Cost Basis of Fuel (Per Gallon) | K4: Gross Earnings | L4: Trip Fuel Cost | M4: Net Earnings | N4: Gross Earnings Per Hour | O4: Net Earnings Per Hour | P4: Gross Earnings Per Mile | Q4: Net Earnings Per Mile
C5: =IF(B5-A5>0,B5-A5,"") | L5: =IFERROR(J5*(H5/I5),"") | M5: =IFERROR(IF(K5-L5>0,K5-L5,""),"") | N5: =IFERROR(K5/(C5/$K$1),"") | O5: =IFERROR(M5/(C5/$K$1),"") | P5: =IFERROR(K5/H5,"") | Q5: =IFERROR((K5-L5)/H5,"")
C6: =IF(B6-A6>0,B6-A6,"") | L6: =IFERROR(J6*(H6/I6),"") | M6: =IFERROR(IF(K6-L6>0,K6-L6,""),"") | N6: =IFERROR(K6/(C6/$K$1),"") | O6: =IFERROR(M6/(C6/$K$1),"") | P6: =IFERROR(K6/H6,"") | Q6: =IFERROR((K6-L6)/H6,"")
C7: =IF(B7-A7>0,B7-A7,"") | L7: =IFERROR(J7*(H7/I7),"") | M7: =IFERROR(IF(K7-L7>0,K7-L7,""),"") | N7: =IFERROR(K7/(C7/$K$1),"") | O7: =IFERROR(M7/(C7/$K$1),"") | P7: =IFERROR(K7/H7,"") | Q7: =IFERROR((K7-L7)/H7,"")
C8: =IF(B8-A8>0,B8-A8,"") | L8: =IFERROR(J8*(H8/I8),"") | M8: =IFERROR(IF(K8-L8>0,K8-L8,""),"") | N8: =IFERROR(K8/(C8/$K$1),"") | O8: =IFERROR(M8/(C8/$K$1),"") | P8: =IFERROR(K8/H8,"") | Q8: =IFERROR((K8-L8)/H8,"")
C9: =IF(B9-A9>0,B9-A9,"") | L9: =IFERROR(J9*(H9/I9),"") | M9: =IFERROR(IF(K9-L9>0,K9-L9,""),"") | N9: =IFERROR(K9/(C9/$K$1),"") | O9: =IFERROR(M9/(C9/$K$1),"") | P9: =IFERROR(K9/H9,"") | Q9: =IFERROR((K9-L9)/H9,"")
C10: =IF(B10-A10>0,B10-A10,"") | L10: =IFERROR(J10*(H10/I10),"") | M10: =IFERROR(IF(K10-L10>0,K10-L10,""),"") | N10: =IFERROR(K10/(C10/$K$1),"") | O10: =IFERROR(M10/(C10/$K$1),"") | P10: =IFERROR(K10/H10,"") | Q10: =IFERROR((K10-L10)/H10,"")
C11: =IF(B11-A11>0,B11-A11,"") | L11: =IFERROR(J11*(H11/I11),"") | M11: =IFERROR(IF(K11-L11>0,K11-L11,""),"") | N11: =IFERROR(K11/(C11/$K$1),"") | O11: =IFERROR(M11/(C11/$K$1),"") | P11: =IFERROR(K11/H11,"") | Q11: =IFERROR((K11-L11)/H11,"")
C12: =IF(B12-A12>0,B12-A12,"") | L12: =IFERROR(J12*(H12/I12),"") | M12: =IFERROR(IF(K12-L12>0,K12-L12,""),"") | N12: =IFERROR(K12/(C12/$K$1),"") | O12: =IFERROR(M12/(C12/$K$1),"") | P12: =IFERROR(K12/H12,"") | Q12: =IFERROR((K12-L12)/H12,"")
C13: =IF(B13-A13>0,B13-A13,"") | L13: =IFERROR(J13*(H13/I13),"") | M13: =IFERROR(IF(K13-L13>0,K13-L13,""),"") | N13: =IFERROR(K13/(C13/$K$1),"") | O13: =IFERROR(M13/(C13/$K$1),"") | P13: =IFERROR(K13/H13,"") | Q13: =IFERROR((K13-L13)/H13,"")
C14: =IF(B14-A14>0,B14-A14,"") | L14: =IFERROR(J14*(H14/I14),"") | M14: =IFERROR(IF(K14-L14>0,K14-L14,""),"") | N14: =IFERROR(K14/(C14/$K$1),"") | O14: =IFERROR(M14/(C14/$K$1),"") | P14: =IFERROR(K14/H14,"") | Q14: =IFERROR((K14-L14)/H14,"")
C15: =IF(B15-A15>0,B15-A15,"") | L15: =IFERROR(J15*(H15/I15),"") | M15: =IFERROR(IF(K15-L15>0,K15-L15,""),"") | N15: =IFERROR(K15/(C15/$K$1),"") | O15: =IFERROR(M15/(C15/$K$1),"") | P15: =IFERROR(K15/H15,"") | Q15: =IFERROR((K15-L15)/H15,"")
C16: =IF(B16-A16>0,B16-A16,"") | L16: =IFERROR(J16*(H16/I16),"") | M16: =IFERROR(IF(K16-L16>0,K16-L16,""),"") | N16: =IFERROR(K16/(C16/$K$1),"") | O16: =IFERROR(M16/(C16/$K$1),"") | P16: =IFERROR(K16/H16,"") | Q16: =IFERROR((K16-L16)/H16,"")
... C505: =IF(B505-A505>0,B505-A505,"") | L505: =IFERROR(J505*(H505/I505),"") | M505: =IFERROR(IF(K505-L505>0,K505-L505,""),"") | N505: =IFERROR(K505/(C505/$K$1),"") | O505: =IFERROR(M505/(C505/$K$1),"") | P505: =IFERROR(K505/H505,"") | Q505: =IFERROR((K505-L505)/H505,"")

Sheet JUN
A1: JUNE | C1: =Summary!C2 -> 0 | K1: 0.041666667 | L1: Total Gross Earnings | M1: =SUM(K5:K505) -> 0 | N1: Total Time | O1: =SUM(C5:C505) -> 0 | P1: Total Mileage | Q1: =SUM(H5:H505) -> 0
L2: Total Fuel Cost | M2: =SUM(L:L) -> 0 | N2: Average Gross Per Hour | O2: =IFERROR(M1/(O1/$K$1),"") | P2: Gross Earnings Per Mile | Q2: =IFERROR(M1/Q1,"")
L3: Total Net Earnings | M3: =M1-M2 -> 0 | N3: Average Net Per Hour | O3: =IFERROR((M1-M2)/(O1/$K$1),"") | P3: Net Earnings Per Mile | Q3: =IFERROR((M1-M2)/Q1,"")
A4: Start Time | B4: End Time | C4: Trip Duration | D4: Vehicle Used | E4: Platform | F4: Accepted Offers | G4: Deliveries/Rides | H4: Total Trip Distance | I4: Trip Average MPG | J4: Current Cost Basis of Fuel (Per Gallon) | K4: Gross Earnings | L4: Trip Fuel Cost | M4: Net Earnings | N4: Gross Earnings Per Hour | O4: Net Earnings Per Hour | P4: Gross Earnings Per Mile | Q4: Net Earnings Per Mile
C5: =IF(B5-A5>0,B5-A5,"") | L5: =IFERROR(J5*(H5/I5),"") | M5: =IFERROR(IF(K5-L5>0,K5-L5,""),"") | N5: =IFERROR(K5/(C5/$K$1),"") | O5: =IFERROR(M5/(C5/$K$1),"") | P5: =IFERROR(K5/H5,"") | Q5: =IFERROR((K5-L5)/H5,"")
C6: =IF(B6-A6>0,B6-A6,"") | L6: =IFERROR(J6*(H6/I6),"") | M6: =IFERROR(IF(K6-L6>0,K6-L6,""),"") | N6: =IFERROR(K6/(C6/$K$1),"") | O6: =IFERROR(M6/(C6/$K$1),"") | P6: =IFERROR(K6/H6,"") | Q6: =IFERROR((K6-L6)/H6,"")
C7: =IF(B7-A7>0,B7-A7,"") | L7: =IFERROR(J7*(H7/I7),"") | M7: =IFERROR(IF(K7-L7>0,K7-L7,""),"") | N7: =IFERROR(K7/(C7/$K$1),"") | O7: =IFERROR(M7/(C7/$K$1),"") | P7: =IFERROR(K7/H7,"") | Q7: =IFERROR((K7-L7)/H7,"")
C8: =IF(B8-A8>0,B8-A8,"") | L8: =IFERROR(J8*(H8/I8),"") | M8: =IFERROR(IF(K8-L8>0,K8-L8,""),"") | N8: =IFERROR(K8/(C8/$K$1),"") | O8: =IFERROR(M8/(C8/$K$1),"") | P8: =IFERROR(K8/H8,"") | Q8: =IFERROR((K8-L8)/H8,"")
C9: =IF(B9-A9>0,B9-A9,"") | L9: =IFERROR(J9*(H9/I9),"") | M9: =IFERROR(IF(K9-L9>0,K9-L9,""),"") | N9: =IFERROR(K9/(C9/$K$1),"") | O9: =IFERROR(M9/(C9/$K$1),"") | P9: =IFERROR(K9/H9,"") | Q9: =IFERROR((K9-L9)/H9,"")
C10: =IF(B10-A10>0,B10-A10,"") | L10: =IFERROR(J10*(H10/I10),"") | M10: =IFERROR(IF(K10-L10>0,K10-L10,""),"") | N10: =IFERROR(K10/(C10/$K$1),"") | O10: =IFERROR(M10/(C10/$K$1),"") | P10: =IFERROR(K10/H10,"") | Q10: =IFERROR((K10-L10)/H10,"")
C11: =IF(B11-A11>0,B11-A11,"") | L11: =IFERROR(J11*(H11/I11),"") | M11: =IFERROR(IF(K11-L11>0,K11-L11,""),"") | N11: =IFERROR(K11/(C11/$K$1),"") | O11: =IFERROR(M11/(C11/$K$1),"") | P11: =IFERROR(K11/H11,"") | Q11: =IFERROR((K11-L11)/H11,"")
C12: =IF(B12-A12>0,B12-A12,"") | L12: =IFERROR(J12*(H12/I12),"") | M12: =IFERROR(IF(K12-L12>0,K12-L12,""),"") | N12: =IFERROR(K12/(C12/$K$1),"") | O12: =IFERROR(M12/(C12/$K$1),"") | P12: =IFERROR(K12/H12,"") | Q12: =IFERROR((K12-L12)/H12,"")
C13: =IF(B13-A13>0,B13-A13,"") | L13: =IFERROR(J13*(H13/I13),"") | M13: =IFERROR(IF(K13-L13>0,K13-L13,""),"") | N13: =IFERROR(K13/(C13/$K$1),"") | O13: =IFERROR(M13/(C13/$K$1),"") | P13: =IFERROR(K13/H13,"") | Q13: =IFERROR((K13-L13)/H13,"")
C14: =IF(B14-A14>0,B14-A14,"") | L14: =IFERROR(J14*(H14/I14),"") | M14: =IFERROR(IF(K14-L14>0,K14-L14,""),"") | N14: =IFERROR(K14/(C14/$K$1),"") | O14: =IFERROR(M14/(C14/$K$1),"") | P14: =IFERROR(K14/H14,"") | Q14: =IFERROR((K14-L14)/H14,"")
C15: =IF(B15-A15>0,B15-A15,"") | L15: =IFERROR(J15*(H15/I15),"") | M15: =IFERROR(IF(K15-L15>0,K15-L15,""),"") | N15: =IFERROR(K15/(C15/$K$1),"") | O15: =IFERROR(M15/(C15/$K$1),"") | P15: =IFERROR(K15/H15,"") | Q15: =IFERROR((K15-L15)/H15,"")
C16: =IF(B16-A16>0,B16-A16,"") | L16: =IFERROR(J16*(H16/I16),"") | M16: =IFERROR(IF(K16-L16>0,K16-L16,""),"") | N16: =IFERROR(K16/(C16/$K$1),"") | O16: =IFERROR(M16/(C16/$K$1),"") | P16: =IFERROR(K16/H16,"") | Q16: =IFERROR((K16-L16)/H16,"")
... C505: =IF(B505-A505>0,B505-A505,"") | L505: =IFERROR(J505*(H505/I505),"") | M505: =IFERROR(IF(K505-L505>0,K505-L505,""),"") | N505: =IFERROR(K505/(C505/$K$1),"") | O505: =IFERROR(M505/(C505/$K$1),"") | P505: =IFERROR(K505/H505,"") | Q505: =IFERROR((K505-L505)/H505,"")

Sheet JLY
A1: JULY | C1: =Summary!C2 -> 0 | K1: 0.041666667 | L1: Total Gross Earnings | M1: =SUM(K5:K505) -> 0 | N1: Total Time | O1: =SUM(C5:C505) -> 0 | P1: Total Mileage | Q1: =SUM(H5:H505) -> 0
L2: Total Fuel Cost | M2: =SUM(L:L) -> 0 | N2: Average Gross Per Hour | O2: =IFERROR(M1/(O1/$K$1),"") | P2: Gross Earnings Per Mile | Q2: =IFERROR(M1/Q1,"")
L3: Total Net Earnings | M3: =M1-M2 -> 0 | N3: Average Net Per Hour | O3: =IFERROR((M1-M2)/(O1/$K$1),"") | P3: Net Earnings Per Mile | Q3: =IFERROR((M1-M2)/Q1,"")
A4: Start Time | B4: End Time | C4: Trip Duration | D4: Vehicle Used | E4: Platform | F4: Accepted Offers | G4: Deliveries/Rides | H4: Total Trip Distance | I4: Trip Average MPG | J4: Current Cost Basis of Fuel (Per Gallon) | K4: Gross Earnings | L4: Trip Fuel Cost | M4: Net Earnings | N4: Gross Earnings Per Hour | O4: Net Earnings Per Hour | P4: Gross Earnings Per Mile | Q4: Net Earnings Per Mile
C5: =IF(B5-A5>0,B5-A5,"") | L5: =IFERROR(J5*(H5/I5),"") | M5: =IFERROR(IF(K5-L5>0,K5-L5,""),"") | N5: =IFERROR(K5/(C5/$K$1),"") | O5: =IFERROR(M5/(C5/$K$1),"") | P5: =IFERROR(K5/H5,"") | Q5: =IFERROR((K5-L5)/H5,"")
C6: =IF(B6-A6>0,B6-A6,"") | L6: =IFERROR(J6*(H6/I6),"") | M6: =IFERROR(IF(K6-L6>0,K6-L6,""),"") | N6: =IFERROR(K6/(C6/$K$1),"") | O6: =IFERROR(M6/(C6/$K$1),"") | P6: =IFERROR(K6/H6,"") | Q6: =IFERROR((K6-L6)/H6,"")
C7: =IF(B7-A7>0,B7-A7,"") | L7: =IFERROR(J7*(H7/I7),"") | M7: =IFERROR(IF(K7-L7>0,K7-L7,""),"") | N7: =IFERROR(K7/(C7/$K$1),"") | O7: =IFERROR(M7/(C7/$K$1),"") | P7: =IFERROR(K7/H7,"") | Q7: =IFERROR((K7-L7)/H7,"")
C8: =IF(B8-A8>0,B8-A8,"") | L8: =IFERROR(J8*(H8/I8),"") | M8: =IFERROR(IF(K8-L8>0,K8-L8,""),"") | N8: =IFERROR(K8/(C8/$K$1),"") | O8: =IFERROR(M8/(C8/$K$1),"") | P8: =IFERROR(K8/H8,"") | Q8: =IFERROR((K8-L8)/H8,"")
C9: =IF(B9-A9>0,B9-A9,"") | L9: =IFERROR(J9*(H9/I9),"") | M9: =IFERROR(IF(K9-L9>0,K9-L9,""),"") | N9: =IFERROR(K9/(C9/$K$1),"") | O9: =IFERROR(M9/(C9/$K$1),"") | P9: =IFERROR(K9/H9,"") | Q9: =IFERROR((K9-L9)/H9,"")
C10: =IF(B10-A10>0,B10-A10,"") | L10: =IFERROR(J10*(H10/I10),"") | M10: =IFERROR(IF(K10-L10>0,K10-L10,""),"") | N10: =IFERROR(K10/(C10/$K$1),"") | O10: =IFERROR(M10/(C10/$K$1),"") | P10: =IFERROR(K10/H10,"") | Q10: =IFERROR((K10-L10)/H10,"")
C11: =IF(B11-A11>0,B11-A11,"") | L11: =IFERROR(J11*(H11/I11),"") | M11: =IFERROR(IF(K11-L11>0,K11-L11,""),"") | N11: =IFERROR(K11/(C11/$K$1),"") | O11: =IFERROR(M11/(C11/$K$1),"") | P11: =IFERROR(K11/H11,"") | Q11: =IFERROR((K11-L11)/H11,"")
C12: =IF(B12-A12>0,B12-A12,"") | L12: =IFERROR(J12*(H12/I12),"") | M12: =IFERROR(IF(K12-L12>0,K12-L12,""),"") | N12: =IFERROR(K12/(C12/$K$1),"") | O12: =IFERROR(M12/(C12/$K$1),"") | P12: =IFERROR(K12/H12,"") | Q12: =IFERROR((K12-L12)/H12,"")
C13: =IF(B13-A13>0,B13-A13,"") | L13: =IFERROR(J13*(H13/I13),"") | M13: =IFERROR(IF(K13-L13>0,K13-L13,""),"") | N13: =IFERROR(K13/(C13/$K$1),"") | O13: =IFERROR(M13/(C13/$K$1),"") | P13: =IFERROR(K13/H13,"") | Q13: =IFERROR((K13-L13)/H13,"")
C14: =IF(B14-A14>0,B14-A14,"") | L14: =IFERROR(J14*(H14/I14),"") | M14: =IFERROR(IF(K14-L14>0,K14-L14,""),"") | N14: =IFERROR(K14/(C14/$K$1),"") | O14: =IFERROR(M14/(C14/$K$1),"") | P14: =IFERROR(K14/H14,"") | Q14: =IFERROR((K14-L14)/H14,"")
C15: =IF(B15-A15>0,B15-A15,"") | L15: =IFERROR(J15*(H15/I15),"") | M15: =IFERROR(IF(K15-L15>0,K15-L15,""),"") | N15: =IFERROR(K15/(C15/$K$1),"") | O15: =IFERROR(M15/(C15/$K$1),"") | P15: =IFERROR(K15/H15,"") | Q15: =IFERROR((K15-L15)/H15,"")
C16: =IF(B16-A16>0,B16-A16,"") | L16: =IFERROR(J16*(H16/I16),"") | M16: =IFERROR(IF(K16-L16>0,K16-L16,""),"") | N16: =IFERROR(K16/(C16/$K$1),"") | O16: =IFERROR(M16/(C16/$K$1),"") | P16: =IFERROR(K16/H16,"") | Q16: =IFERROR((K16-L16)/H16,"")
... C505: =IF(B505-A505>0,B505-A505,"") | L505: =IFERROR(J505*(H505/I505),"") | M505: =IFERROR(IF(K505-L505>0,K505-L505,""),"") | N505: =IFERROR(K505/(C505/$K$1),"") | O505: =IFERROR(M505/(C505/$K$1),"") | P505: =IFERROR(K505/H505,"") | Q505: =IFERROR((K505-L505)/H505,"")

Sheet AUG
A1: AUGUST | C1: =Summary!C2 -> 0 | K1: 0.041666667 | L1: Total Gross Earnings | M1: =SUM(K5:K505) -> 0 | N1: Total Time | O1: =SUM(C5:C505) -> 0 | P1: Total Mileage | Q1: =SUM(H5:H505) -> 0
L2: Total Fuel Cost | M2: =SUM(L:L) -> 0 | N2: Average Gross Per Hour | O2: =IFERROR(M1/(O1/$K$1),"") | P2: Gross Earnings Per Mile | Q2: =IFERROR(M1/Q1,"")
L3: Total Net Earnings | M3: =M1-M2 -> 0 | N3: Average Net Per Hour | O3: =IFERROR((M1-M2)/(O1/$K$1),"") | P3: Net Earnings Per Mile | Q3: =IFERROR((M1-M2)/Q1,"")
A4: Start Time | B4: End Time | C4: Trip Duration | D4: Vehicle Used | E4: Platform | F4: Accepted Offers | G4: Deliveries/Rides | H4: Total Trip Distance | I4: Trip Average MPG | J4: Current Cost Basis of Fuel (Per Gallon) | K4: Gross Earnings | L4: Trip Fuel Cost | M4: Net Earnings | N4: Gross Earnings Per Hour | O4: Net Earnings Per Hour | P4: Gross Earnings Per Mile | Q4: Net Earnings Per Mile
C5: =IF(B5-A5>0,B5-A5,"") | L5: =IFERROR(J5*(H5/I5),"") | M5: =IFERROR(IF(K5-L5>0,K5-L5,""),"") | N5: =IFERROR(K5/(C5/$K$1),"") | O5: =IFERROR(M5/(C5/$K$1),"") | P5: =IFERROR(K5/H5,"") | Q5: =IFERROR((K5-L5)/H5,"")
C6: =IF(B6-A6>0,B6-A6,"") | L6: =IFERROR(J6*(H6/I6),"") | M6: =IFERROR(IF(K6-L6>0,K6-L6,""),"") | N6: =IFERROR(K6/(C6/$K$1),"") | O6: =IFERROR(M6/(C6/$K$1),"") | P6: =IFERROR(K6/H6,"") | Q6: =IFERROR((K6-L6)/H6,"")
C7: =IF(B7-A7>0,B7-A7,"") | L7: =IFERROR(J7*(H7/I7),"") | M7: =IFERROR(IF(K7-L7>0,K7-L7,""),"") | N7: =IFERROR(K7/(C7/$K$1),"") | O7: =IFERROR(M7/(C7/$K$1),"") | P7: =IFERROR(K7/H7,"") | Q7: =IFERROR((K7-L7)/H7,"")
C8: =IF(B8-A8>0,B8-A8,"") | L8: =IFERROR(J8*(H8/I8),"") | M8: =IFERROR(IF(K8-L8>0,K8-L8,""),"") | N8: =IFERROR(K8/(C8/$K$1),"") | O8: =IFERROR(M8/(C8/$K$1),"") | P8: =IFERROR(K8/H8,"") | Q8: =IFERROR((K8-L8)/H8,"")
C9: =IF(B9-A9>0,B9-A9,"") | L9: =IFERROR(J9*(H9/I9),"") | M9: =IFERROR(IF(K9-L9>0,K9-L9,""),"") | N9: =IFERROR(K9/(C9/$K$1),"") | O9: =IFERROR(M9/(C9/$K$1),"") | P9: =IFERROR(K9/H9,"") | Q9: =IFERROR((K9-L9)/H9,"")
C10: =IF(B10-A10>0,B10-A10,"") | L10: =IFERROR(J10*(H10/I10),"") | M10: =IFERROR(IF(K10-L10>0,K10-L10,""),"") | N10: =IFERROR(K10/(C10/$K$1),"") | O10: =IFERROR(M10/(C10/$K$1),"") | P10: =IFERROR(K10/H10,"") | Q10: =IFERROR((K10-L10)/H10,"")
C11: =IF(B11-A11>0,B11-A11,"") | L11: =IFERROR(J11*(H11/I11),"") | M11: =IFERROR(IF(K11-L11>0,K11-L11,""),"") | N11: =IFERROR(K11/(C11/$K$1),"") | O11: =IFERROR(M11/(C11/$K$1),"") | P11: =IFERROR(K11/H11,"") | Q11: =IFERROR((K11-L11)/H11,"")
C12: =IF(B12-A12>0,B12-A12,"") | L12: =IFERROR(J12*(H12/I12),"") | M12: =IFERROR(IF(K12-L12>0,K12-L12,""),"") | N12: =IFERROR(K12/(C12/$K$1),"") | O12: =IFERROR(M12/(C12/$K$1),"") | P12: =IFERROR(K12/H12,"") | Q12: =IFERROR((K12-L12)/H12,"")
C13: =IF(B13-A13>0,B13-A13,"") | L13: =IFERROR(J13*(H13/I13),"") | M13: =IFERROR(IF(K13-L13>0,K13-L13,""),"") | N13: =IFERROR(K13/(C13/$K$1),"") | O13: =IFERROR(M13/(C13/$K$1),"") | P13: =IFERROR(K13/H13,"") | Q13: =IFERROR((K13-L13)/H13,"")
C14: =IF(B14-A14>0,B14-A14,"") | L14: =IFERROR(J14*(H14/I14),"") | M14: =IFERROR(IF(K14-L14>0,K14-L14,""),"") | N14: =IFERROR(K14/(C14/$K$1),"") | O14: =IFERROR(M14/(C14/$K$1),"") | P14: =IFERROR(K14/H14,"") | Q14: =IFERROR((K14-L14)/H14,"")
C15: =IF(B15-A15>0,B15-A15,"") | L15: =IFERROR(J15*(H15/I15),"") | M15: =IFERROR(IF(K15-L15>0,K15-L15,""),"") | N15: =IFERROR(K15/(C15/$K$1),"") | O15: =IFERROR(M15/(C15/$K$1),"") | P15: =IFERROR(K15/H15,"") | Q15: =IFERROR((K15-L15)/H15,"")
C16: =IF(B16-A16>0,B16-A16,"") | L16: =IFERROR(J16*(H16/I16),"") | M16: =IFERROR(IF(K16-L16>0,K16-L16,""),"") | N16: =IFERROR(K16/(C16/$K$1),"") | O16: =IFERROR(M16/(C16/$K$1),"") | P16: =IFERROR(K16/H16,"") | Q16: =IFERROR((K16-L16)/H16,"")
... C505: =IF(B505-A505>0,B505-A505,"") | L505: =IFERROR(J505*(H505/I505),"") | M505: =IFERROR(IF(K505-L505>0,K505-L505,""),"") | N505: =IFERROR(K505/(C505/$K$1),"") | O505: =IFERROR(M505/(C505/$K$1),"") | P505: =IFERROR(K505/H505,"") | Q505: =IFERROR((K505-L505)/H505,"")

Sheet SEP
A1: SEPTEMBER | C1: =Summary!C2 -> 0 | K1: 0.041666667 | L1: Total Gross Earnings | M1: =SUM(K5:K505) -> 0 | N1: Total Time | O1: =SUM(C5:C505) -> 0 | P1: Total Mileage | Q1: =SUM(H5:H505) -> 0
L2: Total Fuel Cost | M2: =SUM(L:L) -> 0 | N2: Average Gross Per Hour | O2: =IFERROR(M1/(O1/$K$1),"") | P2: Gross Earnings Per Mile | Q2: =IFERROR(M1/Q1,"")
L3: Total Net Earnings | M3: =M1-M2 -> 0 | N3: Average Net Per Hour | O3: =IFERROR((M1-M2)/(O1/$K$1),"") | P3: Net Earnings Per Mile | Q3: =IFERROR((M1-M2)/Q1,"")
A4: Start Time | B4: End Time | C4: Trip Duration | D4: Vehicle Used | E4: Platform | F4: Accepted Offers | G4: Deliveries/Rides | H4: Total Trip Distance | I4: Trip Average MPG | J4: Current Cost Basis of Fuel (Per Gallon) | K4: Gross Earnings | L4: Trip Fuel Cost | M4: Net Earnings | N4: Gross Earnings Per Hour | O4: Net Earnings Per Hour | P4: Gross Earnings Per Mile | Q4: Net Earnings Per Mile
C5: =IF(B5-A5>0,B5-A5,"") | L5: =IFERROR(J5*(H5/I5),"") | M5: =IFERROR(IF(K5-L5>0,K5-L5,""),"") | N5: =IFERROR(K5/(C5/$K$1),"") | O5: =IFERROR(M5/(C5/$K$1),"") | P5: =IFERROR(K5/H5,"") | Q5: =IFERROR((K5-L5)/H5,"")
C6: =IF(B6-A6>0,B6-A6,"") | L6: =IFERROR(J6*(H6/I6),"") | M6: =IFERROR(IF(K6-L6>0,K6-L6,""),"") | N6: =IFERROR(K6/(C6/$K$1),"") | O6: =IFERROR(M6/(C6/$K$1),"") | P6: =IFERROR(K6/H6,"") | Q6: =IFERROR((K6-L6)/H6,"")
C7: =IF(B7-A7>0,B7-A7,"") | L7: =IFERROR(J7*(H7/I7),"") | M7: =IFERROR(IF(K7-L7>0,K7-L7,""),"") | N7: =IFERROR(K7/(C7/$K$1),"") | O7: =IFERROR(M7/(C7/$K$1),"") | P7: =IFERROR(K7/H7,"") | Q7: =IFERROR((K7-L7)/H7,"")
C8: =IF(B8-A8>0,B8-A8,"") | L8: =IFERROR(J8*(H8/I8),"") | M8: =IFERROR(IF(K8-L8>0,K8-L8,""),"") | N8: =IFERROR(K8/(C8/$K$1),"") | O8: =IFERROR(M8/(C8/$K$1),"") | P8: =IFERROR(K8/H8,"") | Q8: =IFERROR((K8-L8)/H8,"")
C9: =IF(B9-A9>0,B9-A9,"") | L9: =IFERROR(J9*(H9/I9),"") | M9: =IFERROR(IF(K9-L9>0,K9-L9,""),"") | N9: =IFERROR(K9/(C9/$K$1),"") | O9: =IFERROR(M9/(C9/$K$1),"") | P9: =IFERROR(K9/H9,"") | Q9: =IFERROR((K9-L9)/H9,"")
C10: =IF(B10-A10>0,B10-A10,"") | L10: =IFERROR(J10*(H10/I10),"") | M10: =IFERROR(IF(K10-L10>0,K10-L10,""),"") | N10: =IFERROR(K10/(C10/$K$1),"") | O10: =IFERROR(M10/(C10/$K$1),"") | P10: =IFERROR(K10/H10,"") | Q10: =IFERROR((K10-L10)/H10,"")
C11: =IF(B11-A11>0,B11-A11,"") | L11: =IFERROR(J11*(H11/I11),"") | M11: =IFERROR(IF(K11-L11>0,K11-L11,""),"") | N11: =IFERROR(K11/(C11/$K$1),"") | O11: =IFERROR(M11/(C11/$K$1),"") | P11: =IFERROR(K11/H11,"") | Q11: =IFERROR((K11-L11)/H11,"")
C12: =IF(B12-A12>0,B12-A12,"") | L12: =IFERROR(J12*(H12/I12),"") | M12: =IFERROR(IF(K12-L12>0,K12-L12,""),"") | N12: =IFERROR(K12/(C12/$K$1),"") | O12: =IFERROR(M12/(C12/$K$1),"") | P12: =IFERROR(K12/H12,"") | Q12: =IFERROR((K12-L12)/H12,"")
C13: =IF(B13-A13>0,B13-A13,"") | L13: =IFERROR(J13*(H13/I13),"") | M13: =IFERROR(IF(K13-L13>0,K13-L13,""),"") | N13: =IFERROR(K13/(C13/$K$1),"") | O13: =IFERROR(M13/(C13/$K$1),"") | P13: =IFERROR(K13/H13,"") | Q13: =IFERROR((K13-L13)/H13,"")
C14: =IF(B14-A14>0,B14-A14,"") | L14: =IFERROR(J14*(H14/I14),"") | M14: =IFERROR(IF(K14-L14>0,K14-L14,""),"") | N14: =IFERROR(K14/(C14/$K$1),"") | O14: =IFERROR(M14/(C14/$K$1),"") | P14: =IFERROR(K14/H14,"") | Q14: =IFERROR((K14-L14)/H14,"")
C15: =IF(B15-A15>0,B15-A15,"") | L15: =IFERROR(J15*(H15/I15),"") | M15: =IFERROR(IF(K15-L15>0,K15-L15,""),"") | N15: =IFERROR(K15/(C15/$K$1),"") | O15: =IFERROR(M15/(C15/$K$1),"") | P15: =IFERROR(K15/H15,"") | Q15: =IFERROR((K15-L15)/H15,"")
C16: =IF(B16-A16>0,B16-A16,"") | L16: =IFERROR(J16*(H16/I16),"") | M16: =IFERROR(IF(K16-L16>0,K16-L16,""),"") | N16: =IFERROR(K16/(C16/$K$1),"") | O16: =IFERROR(M16/(C16/$K$1),"") | P16: =IFERROR(K16/H16,"") | Q16: =IFERROR((K16-L16)/H16,"")
... C505: =IF(B505-A505>0,B505-A505,"") | L505: =IFERROR(J505*(H505/I505),"") | M505: =IFERROR(IF(K505-L505>0,K505-L505,""),"") | N505: =IFERROR(K505/(C505/$K$1),"") | O505: =IFERROR(M505/(C505/$K$1),"") | P505: =IFERROR(K505/H505,"") | Q505: =IFERROR((K505-L505)/H505,"")

Sheet OCT
A1: OCTOBER | C1: =Summary!C2 -> 0 | K1: 0.041666667 | L1: Total Gross Earnings | M1: =SUM(K5:K505) -> 0 | N1: Total Time | O1: =SUM(C5:C505) -> 0 | P1: Total Mileage | Q1: =SUM(H5:H505) -> 0
L2: Total Fuel Cost | M2: =SUM(L:L) -> 0 | N2: Average Gross Per Hour | O2: =IFERROR(M1/(O1/$K$1),"") | P2: Gross Earnings Per Mile | Q2: =IFERROR(M1/Q1,"")
L3: Total Net Earnings | M3: =M1-M2 -> 0 | N3: Average Net Per Hour | O3: =IFERROR((M1-M2)/(O1/$K$1),"") | P3: Net Earnings Per Mile | Q3: =IFERROR((M1-M2)/Q1,"")
A4: Start Time | B4: End Time | C4: Trip Duration | D4: Vehicle Used | E4: Platform | F4: Accepted Offers | G4: Deliveries/Rides | H4: Total Trip Distance | I4: Trip Average MPG | J4: Current Cost Basis of Fuel (Per Gallon) | K4: Gross Earnings | L4: Trip Fuel Cost | M4: Net Earnings | N4: Gross Earnings Per Hour | O4: Net Earnings Per Hour | P4: Gross Earnings Per Mile | Q4: Net Earnings Per Mile
C5: =IF(B5-A5>0,B5-A5,"") | L5: =IFERROR(J5*(H5/I5),"") | M5: =IFERROR(IF(K5-L5>0,K5-L5,""),"") | N5: =IFERROR(K5/(C5/$K$1),"") | O5: =IFERROR(M5/(C5/$K$1),"") | P5: =IFERROR(K5/H5,"") | Q5: =IFERROR((K5-L5)/H5,"")
C6: =IF(B6-A6>0,B6-A6,"") | L6: =IFERROR(J6*(H6/I6),"") | M6: =IFERROR(IF(K6-L6>0,K6-L6,""),"") | N6: =IFERROR(K6/(C6/$K$1),"") | O6: =IFERROR(M6/(C6/$K$1),"") | P6: =IFERROR(K6/H6,"") | Q6: =IFERROR((K6-L6)/H6,"")
C7: =IF(B7-A7>0,B7-A7,"") | L7: =IFERROR(J7*(H7/I7),"") | M7: =IFERROR(IF(K7-L7>0,K7-L7,""),"") | N7: =IFERROR(K7/(C7/$K$1),"") | O7: =IFERROR(M7/(C7/$K$1),"") | P7: =IFERROR(K7/H7,"") | Q7: =IFERROR((K7-L7)/H7,"")
C8: =IF(B8-A8>0,B8-A8,"") | L8: =IFERROR(J8*(H8/I8),"") | M8: =IFERROR(IF(K8-L8>0,K8-L8,""),"") | N8: =IFERROR(K8/(C8/$K$1),"") | O8: =IFERROR(M8/(C8/$K$1),"") | P8: =IFERROR(K8/H8,"") | Q8: =IFERROR((K8-L8)/H8,"")
C9: =IF(B9-A9>0,B9-A9,"") | L9: =IFERROR(J9*(H9/I9),"") | M9: =IFERROR(IF(K9-L9>0,K9-L9,""),"") | N9: =IFERROR(K9/(C9/$K$1),"") | O9: =IFERROR(M9/(C9/$K$1),"") | P9: =IFERROR(K9/H9,"") | Q9: =IFERROR((K9-L9)/H9,"")
C10: =IF(B10-A10>0,B10-A10,"") | L10: =IFERROR(J10*(H10/I10),"") | M10: =IFERROR(IF(K10-L10>0,K10-L10,""),"") | N10: =IFERROR(K10/(C10/$K$1),"") | O10: =IFERROR(M10/(C10/$K$1),"") | P10: =IFERROR(K10/H10,"") | Q10: =IFERROR((K10-L10)/H10,"")
C11: =IF(B11-A11>0,B11-A11,"") | L11: =IFERROR(J11*(H11/I11),"") | M11: =IFERROR(IF(K11-L11>0,K11-L11,""),"") | N11: =IFERROR(K11/(C11/$K$1),"") | O11: =IFERROR(M11/(C11/$K$1),"") | P11: =IFERROR(K11/H11,"") | Q11: =IFERROR((K11-L11)/H11,"")
C12: =IF(B12-A12>0,B12-A12,"") | L12: =IFERROR(J12*(H12/I12),"") | M12: =IFERROR(IF(K12-L12>0,K12-L12,""),"") | N12: =IFERROR(K12/(C12/$K$1),"") | O12: =IFERROR(M12/(C12/$K$1),"") | P12: =IFERROR(K12/H12,"") | Q12: =IFERROR((K12-L12)/H12,"")
C13: =IF(B13-A13>0,B13-A13,"") | L13: =IFERROR(J13*(H13/I13),"") | M13: =IFERROR(IF(K13-L13>0,K13-L13,""),"") | N13: =IFERROR(K13/(C13/$K$1),"") | O13: =IFERROR(M13/(C13/$K$1),"") | P13: =IFERROR(K13/H13,"") | Q13: =IFERROR((K13-L13)/H13,"")
C14: =IF(B14-A14>0,B14-A14,"") | L14: =IFERROR(J14*(H14/I14),"") | M14: =IFERROR(IF(K14-L14>0,K14-L14,""),"") | N14: =IFERROR(K14/(C14/$K$1),"") | O14: =IFERROR(M14/(C14/$K$1),"") | P14: =IFERROR(K14/H14,"") | Q14: =IFERROR((K14-L14)/H14,"")
C15: =IF(B15-A15>0,B15-A15,"") | L15: =IFERROR(J15*(H15/I15),"") | M15: =IFERROR(IF(K15-L15>0,K15-L15,""),"") | N15: =IFERROR(K15/(C15/$K$1),"") | O15: =IFERROR(M15/(C15/$K$1),"") | P15: =IFERROR(K15/H15,"") | Q15: =IFERROR((K15-L15)/H15,"")
C16: =IF(B16-A16>0,B16-A16,"") | L16: =IFERROR(J16*(H16/I16),"") | M16: =IFERROR(IF(K16-L16>0,K16-L16,""),"") | N16: =IFERROR(K16/(C16/$K$1),"") | O16: =IFERROR(M16/(C16/$K$1),"") | P16: =IFERROR(K16/H16,"") | Q16: =IFERROR((K16-L16)/H16,"")
... C505: =IF(B505-A505>0,B505-A505,"") | L505: =IFERROR(J505*(H505/I505),"") | M505: =IFERROR(IF(K505-L505>0,K505-L505,""),"") | N505: =IFERROR(K505/(C505/$K$1),"") | O505: =IFERROR(M505/(C505/$K$1),"") | P505: =IFERROR(K505/H505,"") | Q505: =IFERROR((K505-L505)/H505,"")

Sheet NOV
A1: NOVEMBER | C1: =Summary!C2 -> 0 | K1: 0.041666667 | L1: Total Gross Earnings | M1: =SUM(K5:K505) -> 0 | N1: Total Time | O1: =SUM(C5:C505) -> 0 | P1: Total Mileage | Q1: =SUM(H5:H505) -> 0
L2: Total Fuel Cost | M2: =SUM(L:L) -> 0 | N2: Average Gross Per Hour | O2: =IFERROR(M1/(O1/$K$1),"") | P2: Gross Earnings Per Mile | Q2: =IFERROR(M1/Q1,"")
L3: Total Net Earnings | M3: =M1-M2 -> 0 | N3: Average Net Per Hour | O3: =IFERROR((M1-M2)/(O1/$K$1),"") | P3: Net Earnings Per Mile | Q3: =IFERROR((M1-M2)/Q1,"")
A4: Start Time | B4: End Time | C4: Trip Duration | D4: Vehicle Used | E4: Platform | F4: Accepted Offers | G4: Deliveries/Rides | H4: Total Trip Distance | I4: Trip Average MPG | J4: Current Cost Basis of Fuel (Per Gallon) | K4: Gross Earnings | L4: Trip Fuel Cost | M4: Net Earnings | N4: Gross Earnings Per Hour | O4: Net Earnings Per Hour | P4: Gross Earnings Per Mile | Q4: Net Earnings Per Mile
C5: =IF(B5-A5>0,B5-A5,"") | L5: =IFERROR(J5*(H5/I5),"") | M5: =IFERROR(IF(K5-L5>0,K5-L5,""),"") | N5: =IFERROR(K5/(C5/$K$1),"") | O5: =IFERROR(M5/(C5/$K$1),"") | P5: =IFERROR(K5/H5,"") | Q5: =IFERROR((K5-L5)/H5,"")
C6: =IF(B6-A6>0,B6-A6,"") | L6: =IFERROR(J6*(H6/I6),"") | M6: =IFERROR(IF(K6-L6>0,K6-L6,""),"") | N6: =IFERROR(K6/(C6/$K$1),"") | O6: =IFERROR(M6/(C6/$K$1),"") | P6: =IFERROR(K6/H6,"") | Q6: =IFERROR((K6-L6)/H6,"")
C7: =IF(B7-A7>0,B7-A7,"") | L7: =IFERROR(J7*(H7/I7),"") | M7: =IFERROR(IF(K7-L7>0,K7-L7,""),"") | N7: =IFERROR(K7/(C7/$K$1),"") | O7: =IFERROR(M7/(C7/$K$1),"") | P7: =IFERROR(K7/H7,"") | Q7: =IFERROR((K7-L7)/H7,"")
C8: =IF(B8-A8>0,B8-A8,"") | L8: =IFERROR(J8*(H8/I8),"") | M8: =IFERROR(IF(K8-L8>0,K8-L8,""),"") | N8: =IFERROR(K8/(C8/$K$1),"") | O8: =IFERROR(M8/(C8/$K$1),"") | P8: =IFERROR(K8/H8,"") | Q8: =IFERROR((K8-L8)/H8,"")
C9: =IF(B9-A9>0,B9-A9,"") | L9: =IFERROR(J9*(H9/I9),"") | M9: =IFERROR(IF(K9-L9>0,K9-L9,""),"") | N9: =IFERROR(K9/(C9/$K$1),"") | O9: =IFERROR(M9/(C9/$K$1),"") | P9: =IFERROR(K9/H9,"") | Q9: =IFERROR((K9-L9)/H9,"")
C10: =IF(B10-A10>0,B10-A10,"") | L10: =IFERROR(J10*(H10/I10),"") | M10: =IFERROR(IF(K10-L10>0,K10-L10,""),"") | N10: =IFERROR(K10/(C10/$K$1),"") | O10: =IFERROR(M10/(C10/$K$1),"") | P10: =IFERROR(K10/H10,"") | Q10: =IFERROR((K10-L10)/H10,"")
C11: =IF(B11-A11>0,B11-A11,"") | L11: =IFERROR(J11*(H11/I11),"") | M11: =IFERROR(IF(K11-L11>0,K11-L11,""),"") | N11: =IFERROR(K11/(C11/$K$1),"") | O11: =IFERROR(M11/(C11/$K$1),"") | P11: =IFERROR(K11/H11,"") | Q11: =IFERROR((K11-L11)/H11,"")
C12: =IF(B12-A12>0,B12-A12,"") | L12: =IFERROR(J12*(H12/I12),"") | M12: =IFERROR(IF(K12-L12>0,K12-L12,""),"") | N12: =IFERROR(K12/(C12/$K$1),"") | O12: =IFERROR(M12/(C12/$K$1),"") | P12: =IFERROR(K12/H12,"") | Q12: =IFERROR((K12-L12)/H12,"")
C13: =IF(B13-A13>0,B13-A13,"") | L13: =IFERROR(J13*(H13/I13),"") | M13: =IFERROR(IF(K13-L13>0,K13-L13,""),"") | N13: =IFERROR(K13/(C13/$K$1),"") | O13: =IFERROR(M13/(C13/$K$1),"") | P13: =IFERROR(K13/H13,"") | Q13: =IFERROR((K13-L13)/H13,"")
C14: =IF(B14-A14>0,B14-A14,"") | L14: =IFERROR(J14*(H14/I14),"") | M14: =IFERROR(IF(K14-L14>0,K14-L14,""),"") | N14: =IFERROR(K14/(C14/$K$1),"") | O14: =IFERROR(M14/(C14/$K$1),"") | P14: =IFERROR(K14/H14,"") | Q14: =IFERROR((K14-L14)/H14,"")
C15: =IF(B15-A15>0,B15-A15,"") | L15: =IFERROR(J15*(H15/I15),"") | M15: =IFERROR(IF(K15-L15>0,K15-L15,""),"") | N15: =IFERROR(K15/(C15/$K$1),"") | O15: =IFERROR(M15/(C15/$K$1),"") | P15: =IFERROR(K15/H15,"") | Q15: =IFERROR((K15-L15)/H15,"")
C16: =IF(B16-A16>0,B16-A16,"") | L16: =IFERROR(J16*(H16/I16),"") | M16: =IFERROR(IF(K16-L16>0,K16-L16,""),"") | N16: =IFERROR(K16/(C16/$K$1),"") | O16: =IFERROR(M16/(C16/$K$1),"") | P16: =IFERROR(K16/H16,"") | Q16: =IFERROR((K16-L16)/H16,"")
... C505: =IF(B505-A505>0,B505-A505,"") | L505: =IFERROR(J505*(H505/I505),"") | M505: =IFERROR(IF(K505-L505>0,K505-L505,""),"") | N505: =IFERROR(K505/(C505/$K$1),"") | O505: =IFERROR(M505/(C505/$K$1),"") | P505: =IFERROR(K505/H505,"") | Q505: =IFERROR((K505-L505)/H505,"")

Sheet DEC
A1: DECEMBER | C1: =Summary!C2 -> 0 | K1: 0.041666667 | L1: Total Gross Earnings | M1: =SUM(K5:K505) -> 0 | N1: Total Time | O1: =SUM(C5:C505) -> 0 | P1: Total Mileage | Q1: =SUM(H5:H505) -> 0
L2: Total Fuel Cost | M2: =SUM(L:L) -> 0 | N2: Average Gross Per Hour | O2: =IFERROR(M1/(O1/$K$1),"") | P2: Gross Earnings Per Mile | Q2: =IFERROR(M1/Q1,"")
L3: Total Net Earnings | M3: =M1-M2 -> 0 | N3: Average Net Per Hour | O3: =IFERROR((M1-M2)/(O1/$K$1),"") | P3: Net Earnings Per Mile | Q3: =IFERROR((M1-M2)/Q1,"")
A4: Start Time | B4: End Time | C4: Trip Duration | D4: Vehicle Used | E4: Platform | F4: Accepted Offers | G4: Deliveries/Rides | H4: Total Trip Distance | I4: Trip Average MPG | J4: Current Cost Basis of Fuel (Per Gallon) | K4: Gross Earnings | L4: Trip Fuel Cost | M4: Net Earnings | N4: Gross Earnings Per Hour | O4: Net Earnings Per Hour | P4: Gross Earnings Per Mile | Q4: Net Earnings Per Mile
C5: =IF(B5-A5>0,B5-A5,"") | L5: =IFERROR(J5*(H5/I5),"") | M5: =IFERROR(IF(K5-L5>0,K5-L5,""),"") | N5: =IFERROR(K5/(C5/$K$1),"") | O5: =IFERROR(M5/(C5/$K$1),"") | P5: =IFERROR(K5/H5,"") | Q5: =IFERROR((K5-L5)/H5,"")
C6: =IF(B6-A6>0,B6-A6,"") | L6: =IFERROR(J6*(H6/I6),"") | M6: =IFERROR(IF(K6-L6>0,K6-L6,""),"") | N6: =IFERROR(K6/(C6/$K$1),"") | O6: =IFERROR(M6/(C6/$K$1),"") | P6: =IFERROR(K6/H6,"") | Q6: =IFERROR((K6-L6)/H6,"")
C7: =IF(B7-A7>0,B7-A7,"") | L7: =IFERROR(J7*(H7/I7),"") | M7: =IFERROR(IF(K7-L7>0,K7-L7,""),"") | N7: =IFERROR(K7/(C7/$K$1),"") | O7: =IFERROR(M7/(C7/$K$1),"") | P7: =IFERROR(K7/H7,"") | Q7: =IFERROR((K7-L7)/H7,"")
C8: =IF(B8-A8>0,B8-A8,"") | L8: =IFERROR(J8*(H8/I8),"") | M8: =IFERROR(IF(K8-L8>0,K8-L8,""),"") | N8: =IFERROR(K8/(C8/$K$1),"") | O8: =IFERROR(M8/(C8/$K$1),"") | P8: =IFERROR(K8/H8,"") | Q8: =IFERROR((K8-L8)/H8,"")
C9: =IF(B9-A9>0,B9-A9,"") | L9: =IFERROR(J9*(H9/I9),"") | M9: =IFERROR(IF(K9-L9>0,K9-L9,""),"") | N9: =IFERROR(K9/(C9/$K$1),"") | O9: =IFERROR(M9/(C9/$K$1),"") | P9: =IFERROR(K9/H9,"") | Q9: =IFERROR((K9-L9)/H9,"")
C10: =IF(B10-A10>0,B10-A10,"") | L10: =IFERROR(J10*(H10/I10),"") | M10: =IFERROR(IF(K10-L10>0,K10-L10,""),"") | N10: =IFERROR(K10/(C10/$K$1),"") | O10: =IFERROR(M10/(C10/$K$1),"") | P10: =IFERROR(K10/H10,"") | Q10: =IFERROR((K10-L10)/H10,"")
C11: =IF(B11-A11>0,B11-A11,"") | L11: =IFERROR(J11*(H11/I11),"") | M11: =IFERROR(IF(K11-L11>0,K11-L11,""),"") | N11: =IFERROR(K11/(C11/$K$1),"") | O11: =IFERROR(M11/(C11/$K$1),"") | P11: =IFERROR(K11/H11,"") | Q11: =IFERROR((K11-L11)/H11,"")
C12: =IF(B12-A12>0,B12-A12,"") | L12: =IFERROR(J12*(H12/I12),"") | M12: =IFERROR(IF(K12-L12>0,K12-L12,""),"") | N12: =IFERROR(K12/(C12/$K$1),"") | O12: =IFERROR(M12/(C12/$K$1),"") | P12: =IFERROR(K12/H12,"") | Q12: =IFERROR((K12-L12)/H12,"")
C13: =IF(B13-A13>0,B13-A13,"") | L13: =IFERROR(J13*(H13/I13),"") | M13: =IFERROR(IF(K13-L13>0,K13-L13,""),"") | N13: =IFERROR(K13/(C13/$K$1),"") | O13: =IFERROR(M13/(C13/$K$1),"") | P13: =IFERROR(K13/H13,"") | Q13: =IFERROR((K13-L13)/H13,"")
C14: =IF(B14-A14>0,B14-A14,"") | L14: =IFERROR(J14*(H14/I14),"") | M14: =IFERROR(IF(K14-L14>0,K14-L14,""),"") | N14: =IFERROR(K14/(C14/$K$1),"") | O14: =IFERROR(M14/(C14/$K$1),"") | P14: =IFERROR(K14/H14,"") | Q14: =IFERROR((K14-L14)/H14,"")
C15: =IF(B15-A15>0,B15-A15,"") | L15: =IFERROR(J15*(H15/I15),"") | M15: =IFERROR(IF(K15-L15>0,K15-L15,""),"") | N15: =IFERROR(K15/(C15/$K$1),"") | O15: =IFERROR(M15/(C15/$K$1),"") | P15: =IFERROR(K15/H15,"") | Q15: =IFERROR((K15-L15)/H15,"")
C16: =IF(B16-A16>0,B16-A16,"") | L16: =IFERROR(J16*(H16/I16),"") | M16: =IFERROR(IF(K16-L16>0,K16-L16,""),"") | N16: =IFERROR(K16/(C16/$K$1),"") | O16: =IFERROR(M16/(C16/$K$1),"") | P16: =IFERROR(K16/H16,"") | Q16: =IFERROR((K16-L16)/H16,"")
... C505: =IF(B505-A505>0,B505-A505,"") | L505: =IFERROR(J505*(H505/I505),"") | M505: =IFERROR(IF(K505-L505>0,K505-L505,""),"") | N505: =IFERROR(K505/(C505/$K$1),"") | O505: =IFERROR(M505/(C505/$K$1),"") | P505: =IFERROR(K505/H505,"") | Q505: =IFERROR((K505-L505)/H505,"")
